{
  "name": "blastoise-mega",
  "caption": "Mega Blastoise",
  "types": [
    "water"
  ],
  "species": "blastoise",
  "gen": "generation-i",
  "color": "blue",
  "default": false,
  "alternate": false,
  "mega": true,
  "height": 1.6,
  "weight": 101.1,
  "baseStats": {
    "hp": 79,
    "attack": 103,
    "defense": 120,
    "special-attack": 135,
    "special-defense": 115,
    "speed": 78
  },
  "evolutionChain": {
    "species": "squirtle",
    "triggers": [],
    "evolvesTo": [
      {
        "species": "wartortle",
        "triggers": [
          "level-up"
        ],
        "evolvesTo": [
          {
            "species": "blastoise",
            "triggers": [
              "level-up"
            ],
            "evolvesTo": []
          }
        ]
      }
    ]
  },
  "flavorText": "Blastoise has water spouts that protrude from its shell.\nThe water spouts are very accurate. They can shoot bullets of\nwater with enough accuracy to strike empty cans from a\ndistance of over 160 feet.",
  "moves": {
    "tackle": [
      "level-up"
    ],
    "tail-whip": [
      "level-up"
    ],
    "bite": [
      "level-up"
    ],
    "roar": [
      "machine"
    ],
    "water-gun": [
      "level-up"
    ],
    "hydro-pump": [
      "level-up"
    ],
    "surf": [
      "machine"
    ],
    "ice-beam": [
      "machine"
    ],
    "blizzard": [
      "machine"
    ],
    "hyper-beam": [
      "machine"
    ],
    "earthquake": [
      "machine"
    ],
    "toxic": [
      "machine"
    ],
    "double-team": [
      "machine"
    ],
    "withdraw": [
      "level-up"
    ],
    "waterfall": [
      "machine"
    ],
    "skull-bash": [
      "level-up"
    ],
    "bubble": [
      "level-up"
    ],
    "rest": [
      "machine"
    ],
    "rock-slide": [
      "machine"
    ],
    "substitute": [
      "machine"
    ],
    "protect": [
      "level-up",
      "machine"
    ],
    "swagger": [
      "machine"
    ],
    "attract": [
      "machine"
    ],
    "sleep-talk": [
      "machine"
    ],
    "return": [
      "machine"
    ],
    "frustration": [
      "machine"
    ],
    "rapid-spin": [
      "level-up"
    ],
    "hidden-power": [
      "machine"
    ],
    "rain-dance": [
      "level-up",
      "machine"
    ],
    "hail": [
      "machine"
    ],
    "facade": [
      "machine"
    ],
    "brick-break": [
      "machine"
    ],
    "hydro-cannon": [
      "tutor"
    ],
    "rock-tomb": [
      "machine"
    ],
    "iron-defense": [
      "level-up"
    ],
    "water-pulse": [
      "level-up"
    ],
    "gyro-ball": [
      "machine"
    ],
    "fling": [
      "machine"
    ],
    "dark-pulse": [
      "machine"
    ],
    "aqua-tail": [
      "level-up"
    ],
    "focus-blast": [
      "machine"
    ],
    "giga-impact": [
      "machine"
    ],
    "flash-cannon": [
      "level-up",
      "machine"
    ],
    "smack-down": [
      "machine"
    ],
    "round": [
      "machine"
    ],
    "scald": [
      "machine"
    ],
    "water-pledge": [
      "tutor"
    ],
    "bulldoze": [
      "machine"
    ],
    "dragon-tail": [
      "machine"
    ],
    "confide": [
      "machine"
    ],
    "work-up": [
      "machine"
    ]
  },
  "abilities": {
    "mega-launcher": 1
  }
}
