{
  "name": "froakie",
  "caption": "Froakie",
  "types": [
    "water"
  ],
  "species": "froakie",
  "gen": "generation-vi",
  "color": "blue",
  "default": true,
  "alternate": false,
  "mega": false,
  "height": 0.3,
  "weight": 7,
  "baseStats": {
    "hp": 41,
    "attack": 56,
    "defense": 40,
    "special-attack": 62,
    "special-defense": 44,
    "speed": 71
  },
  "evolutionChain": {
    "species": "froakie",
    "triggers": [],
    "evolvesTo": [
      {
        "species": "frogadier",
        "triggers": [
          "level-up"
        ],
        "evolvesTo": [
          {
            "species": "greninja",
            "triggers": [
              "level-up"
            ],
            "evolvesTo": []
          }
        ]
      }
    ]
  },
  "flavorText": "It secretes flexible bubbles from its chest and back.\nThe bubbles reduce the damage it would otherwise\ntake when attacked.",
  "moves": {
    "pound": [
      "level-up"
    ],
    "growl": [
      "level-up"
    ],
    "hydro-pump": [
      "level-up"
    ],
    "surf": [
      "machine"
    ],
    "ice-beam": [
      "machine"
    ],
    "blizzard": [
      "machine"
    ],
    "toxic": [
      "machine"
    ],
    "quick-attack": [
      "level-up"
    ],
    "double-team": [
      "level-up",
      "machine"
    ],
    "smokescreen": [
      "level-up"
    ],
    "lick": [
      "level-up"
    ],
    "waterfall": [
      "machine"
    ],
    "bubble": [
      "level-up"
    ],
    "rest": [
      "machine"
    ],
    "rock-slide": [
      "machine"
    ],
    "substitute": [
      "level-up",
      "machine"
    ],
    "thief": [
      "machine"
    ],
    "mind-reader": [
      "egg"
    ],
    "protect": [
      "machine"
    ],
    "swagger": [
      "machine"
    ],
    "attract": [
      "machine"
    ],
    "sleep-talk": [
      "machine"
    ],
    "return": [
      "machine"
    ],
    "frustration": [
      "machine"
    ],
    "hidden-power": [
      "machine"
    ],
    "rain-dance": [
      "machine"
    ],
    "facade": [
      "machine"
    ],
    "taunt": [
      "machine"
    ],
    "camouflage": [
      "egg"
    ],
    "mud-sport": [
      "egg"
    ],
    "rock-tomb": [
      "machine"
    ],
    "aerial-ace": [
      "machine"
    ],
    "bounce": [
      "level-up"
    ],
    "water-sport": [
      "egg"
    ],
    "water-pulse": [
      "level-up"
    ],
    "u-turn": [
      "machine"
    ],
    "fling": [
      "level-up",
      "machine"
    ],
    "toxic-spikes": [
      "egg"
    ],
    "grass-knot": [
      "machine"
    ],
    "smack-down": [
      "level-up",
      "machine"
    ],
    "round": [
      "level-up",
      "machine"
    ],
    "echoed-voice": [
      "machine"
    ],
    "scald": [
      "machine"
    ],
    "acrobatics": [
      "machine"
    ],
    "bestow": [
      "egg"
    ],
    "water-pledge": [
      "tutor"
    ],
    "confide": [
      "machine"
    ],
    "power-up-punch": [
      "egg"
    ],
    "work-up": [
      "machine"
    ]
  },
  "abilities": {
    "torrent": 1,
    "protean": "hidden"
  }
}
