{
  "name": "pumpkaboo-small",
  "caption": "Small Pumpkaboo",
  "types": [
    "ghost",
    "grass"
  ],
  "species": "pumpkaboo",
  "gen": "generation-vi",
  "color": "brown",
  "default": false,
  "alternate": true,
  "mega": false,
  "form": "Small Size",
  "height": 0.3,
  "weight": 3.5,
  "baseStats": {
    "hp": 44,
    "attack": 66,
    "defense": 70,
    "special-attack": 44,
    "special-defense": 55,
    "speed": 56
  },
  "evolutionChain": {
    "species": "pumpkaboo",
    "triggers": [],
    "evolvesTo": [
      {
        "species": "gourgeist",
        "triggers": [
          "trade"
        ],
        "evolvesTo": []
      }
    ]
  },
  "flavorText": "The pumpkin body is inhabited by a spirit\ntrapped in this world. As the sun sets,\nit becomes restless and active.",
  "moves": {
    "flamethrower": [
      "machine"
    ],
    "leech-seed": [
      "level-up"
    ],
    "razor-leaf": [
      "level-up"
    ],
    "solar-beam": [
      "machine"
    ],
    "toxic": [
      "machine"
    ],
    "psychic": [
      "machine"
    ],
    "double-team": [
      "machine"
    ],
    "confuse-ray": [
      "level-up"
    ],
    "light-screen": [
      "machine"
    ],
    "fire-blast": [
      "machine"
    ],
    "dream-eater": [
      "machine"
    ],
    "explosion": [
      "machine"
    ],
    "rest": [
      "machine"
    ],
    "rock-slide": [
      "machine"
    ],
    "substitute": [
      "machine"
    ],
    "thief": [
      "machine"
    ],
    "protect": [
      "machine"
    ],
    "scary-face": [
      "level-up"
    ],
    "sludge-bomb": [
      "machine"
    ],
    "swagger": [
      "machine"
    ],
    "attract": [
      "machine"
    ],
    "sleep-talk": [
      "machine"
    ],
    "return": [
      "machine"
    ],
    "frustration": [
      "machine"
    ],
    "safeguard": [
      "machine"
    ],
    "pain-split": [
      "level-up"
    ],
    "hidden-power": [
      "machine"
    ],
    "sunny-day": [
      "machine"
    ],
    "shadow-ball": [
      "level-up",
      "machine"
    ],
    "will-o-wisp": [
      "machine"
    ],
    "facade": [
      "machine"
    ],
    "nature-power": [
      "machine"
    ],
    "trick": [
      "level-up"
    ],
    "astonish": [
      "level-up"
    ],
    "bullet-seed": [
      "level-up"
    ],
    "gyro-ball": [
      "machine"
    ],
    "worry-seed": [
      "level-up"
    ],
    "dark-pulse": [
      "machine"
    ],
    "seed-bomb": [
      "level-up"
    ],
    "energy-ball": [
      "machine"
    ],
    "shadow-sneak": [
      "level-up"
    ],
    "trick-room": [
      "machine"
    ],
    "grass-knot": [
      "machine"
    ],
    "charge-beam": [
      "machine"
    ],
    "flame-charge": [
      "machine"
    ],
    "round": [
      "machine"
    ],
    "trick-or-treat": [
      "level-up"
    ],
    "confide": [
      "machine"
    ]
  },
  "abilities": {
    "pickup": 1,
    "frisk": 2,
    "insomnia": "hidden"
  }
}
