{
  "name": "talonflame",
  "caption": "Talonflame",
  "types": [
    "fire",
    "flying"
  ],
  "species": "talonflame",
  "gen": "generation-vi",
  "color": "red",
  "default": true,
  "alternate": false,
  "mega": false,
  "height": 1.2,
  "weight": 24.5,
  "baseStats": {
    "hp": 78,
    "attack": 81,
    "defense": 71,
    "special-attack": 74,
    "special-defense": 69,
    "speed": 126
  },
  "evolutionChain": {
    "species": "fletchling",
    "triggers": [],
    "evolvesTo": [
      {
        "species": "fletchinder",
        "triggers": [
          "level-up"
        ],
        "evolvesTo": [
          {
            "species": "talonflame",
            "triggers": [
              "level-up"
            ],
            "evolvesTo": []
          }
        ]
      }
    ]
  },
  "flavorText": "Its tough wings don’t allow fire to pass through\nthem. A long time ago, firefighters’ outfits were\nmade from Talonflame wings.",
  "moves": {
    "razor-wind": [
      "level-up"
    ],
    "swords-dance": [
      "machine"
    ],
    "fly": [
      "machine"
    ],
    "tackle": [
      "level-up"
    ],
    "growl": [
      "level-up"
    ],
    "ember": [
      "level-up"
    ],
    "flamethrower": [
      "machine"
    ],
    "hyper-beam": [
      "machine"
    ],
    "peck": [
      "level-up"
    ],
    "solar-beam": [
      "machine"
    ],
    "toxic": [
      "machine"
    ],
    "agility": [
      "level-up"
    ],
    "quick-attack": [
      "level-up"
    ],
    "double-team": [
      "machine"
    ],
    "fire-blast": [
      "machine"
    ],
    "rest": [
      "machine"
    ],
    "substitute": [
      "machine"
    ],
    "thief": [
      "machine"
    ],
    "flail": [
      "level-up"
    ],
    "protect": [
      "machine"
    ],
    "swagger": [
      "machine"
    ],
    "steel-wing": [
      "level-up",
      "machine"
    ],
    "attract": [
      "machine"
    ],
    "sleep-talk": [
      "machine"
    ],
    "return": [
      "machine"
    ],
    "frustration": [
      "machine"
    ],
    "hidden-power": [
      "machine"
    ],
    "sunny-day": [
      "machine"
    ],
    "will-o-wisp": [
      "machine"
    ],
    "facade": [
      "machine"
    ],
    "taunt": [
      "machine"
    ],
    "overheat": [
      "machine"
    ],
    "aerial-ace": [
      "machine"
    ],
    "bulk-up": [
      "machine"
    ],
    "roost": [
      "level-up",
      "machine"
    ],
    "natural-gift": [
      "level-up"
    ],
    "tailwind": [
      "level-up"
    ],
    "u-turn": [
      "machine"
    ],
    "me-first": [
      "level-up"
    ],
    "flare-blitz": [
      "level-up"
    ],
    "brave-bird": [
      "level-up"
    ],
    "giga-impact": [
      "machine"
    ],
    "flame-charge": [
      "level-up",
      "machine"
    ],
    "round": [
      "machine"
    ],
    "acrobatics": [
      "level-up",
      "machine"
    ],
    "confide": [
      "machine"
    ],
    "work-up": [
      "machine"
    ]
  },
  "abilities": {
    "flame-body": 1,
    "gale-wings": "hidden"
  }
}
