{
  "name": "cross-chop",
  "caption": "Cross Chop",
  "type": "fighting",
  "damageCategory": "physical",
  "power": 100,
  "accuracy": 80,
  "pp": 5,
  "z": false,
  "priority": 0,
  "gen": "generation-ii",
  "effect": {
    "short": "Has an increased chance for a critical hit.",
    "full": "Inflicts [regular damage]{mechanic:regular-damage}.  User's [critical hit]{mechanic:critical-hit} rate is one level higher when using this move."
  },
  "flavorText": "The user delivers a double chop with its forearms\ncrossed. Critical hits land more easily.",
  "flags": [
    "contact",
    "protect",
    "mirror"
  ],
  "target": "selected-pokemon",
  "pokemon": {
    "psyduck": [
      "egg"
    ],
    "mankey": [
      "level-up"
    ],
    "primeape": [
      "level-up"
    ],
    "machop": [
      "level-up"
    ],
    "machoke": [
      "level-up"
    ],
    "machamp": [
      "level-up"
    ],
    "teddiursa": [
      "egg"
    ],
    "elekid": [
      "egg"
    ],
    "magby": [
      "egg"
    ],
    "makuhita": [
      "egg"
    ],
    "riolu": [
      "egg"
    ],
    "croagunk": [
      "egg"
    ],
    "binacle": [
      "level-up"
    ],
    "barbaracle": [
      "level-up"
    ],
    "incineroar": [
      "level-up"
    ]
  }
}
