{
  "name": "relic-song",
  "caption": "Relic Song",
  "type": "normal",
  "damageCategory": "special",
  "power": 75,
  "accuracy": 100,
  "pp": 10,
  "z": false,
  "priority": 0,
  "gen": "generation-v",
  "effect": {
    "short": "Has a 10% chance to put the target to sleep.",
    "full": "Inflicts [regular damage]{mechanic:regular-damage}.  Has a 10% chance to put the target to [sleep]{mechanic:sleep}.\nIf the user is a []{pokemon:meloetta}, it will toggle between Aria and Pirouette Forme."
  },
  "flavorText": "The user sings an ancient song and attacks by\nappealing to the hearts of the listening opposing\nPokémon. This may also induce sleep.",
  "flags": [
    "protect",
    "mirror",
    "sound",
    "authentic"
  ],
  "target": "all-opponents",
  "pokemon": {}
}
