{
  "name": "stone-edge",
  "caption": "Stone Edge",
  "type": "rock",
  "damageCategory": "physical",
  "power": 100,
  "accuracy": 80,
  "pp": 5,
  "z": false,
  "priority": 0,
  "gen": "generation-iv",
  "effect": {
    "short": "Has an increased chance for a critical hit.",
    "full": "Inflicts [regular damage]{mechanic:regular-damage}.  User's [critical hit]{mechanic:critical-hit} rate is one level higher when using this move."
  },
  "flavorText": "The user stabs the target from below with\nsharpened stones. Critical hits land more easily.",
  "flags": [
    "protect",
    "mirror"
  ],
  "target": "selected-pokemon",
  "pokemon": {
    "sandslash": [
      "machine"
    ],
    "nidoqueen": [
      "machine"
    ],
    "nidoking": [
      "machine"
    ],
    "dugtrio": [
      "machine"
    ],
    "primeape": [
      "machine"
    ],
    "machamp": [
      "machine"
    ],
    "geodude": [
      "level-up",
      "machine"
    ],
    "graveler": [
      "level-up",
      "machine"
    ],
    "golem": [
      "level-up",
      "machine"
    ],
    "onix": [
      "level-up",
      "machine"
    ],
    "marowak": [
      "machine"
    ],
    "hitmonlee": [
      "machine"
    ],
    "hitmonchan": [
      "machine"
    ],
    "rhyhorn": [
      "level-up",
      "machine"
    ],
    "rhydon": [
      "level-up",
      "machine"
    ],
    "pinsir": [
      "machine"
    ],
    "tauros": [
      "machine"
    ],
    "gyarados": [
      "machine"
    ],
    "omastar": [
      "machine"
    ],
    "kabutops": [
      "machine"
    ],
    "aerodactyl": [
      "machine"
    ],
    "dragonite": [
      "machine"
    ],
    "mewtwo": [
      "machine"
    ],
    "mew": [
      "machine"
    ],
    "sudowoodo": [
      "level-up",
      "machine"
    ],
    "quagsire": [
      "machine"
    ],
    "gligar": [
      "machine"
    ],
    "steelix": [
      "level-up",
      "machine"
    ],
    "granbull": [
      "machine"
    ],
    "shuckle": [
      "level-up",
      "machine"
    ],
    "heracross": [
      "machine"
    ],
    "ursaring": [
      "machine"
    ],
    "magcargo": [
      "machine"
    ],
    "piloswine": [
      "machine"
    ],
    "corsola": [
      "machine"
    ],
    "donphan": [
      "machine"
    ],
    "hitmontop": [
      "machine"
    ],
    "entei": [
      "machine"
    ],
    "larvitar": [
      "level-up",
      "machine"
    ],
    "pupitar": [
      "level-up",
      "machine"
    ],
    "tyranitar": [
      "level-up",
      "machine"
    ],
    "blaziken": [
      "machine"
    ],
    "swampert": [
      "machine"
    ],
    "breloom": [
      "machine"
    ],
    "hariyama": [
      "machine"
    ],
    "nosepass": [
      "level-up",
      "machine"
    ],
    "mawile": [
      "machine"
    ],
    "lairon": [
      "machine"
    ],
    "aggron": [
      "machine"
    ],
    "camerupt": [
      "machine"
    ],
    "torkoal": [
      "machine"
    ],
    "flygon": [
      "machine"
    ],
    "lunatone": [
      "level-up",
      "machine"
    ],
    "solrock": [
      "level-up",
      "machine"
    ],
    "whiscash": [
      "machine"
    ],
    "claydol": [
      "machine"
    ],
    "cradily": [
      "machine"
    ],
    "armaldo": [
      "machine"
    ],
    "absol": [
      "machine"
    ],
    "relicanth": [
      "machine"
    ],
    "salamence": [
      "machine"
    ],
    "regirock": [
      "level-up",
      "machine"
    ],
    "groudon": [
      "machine"
    ],
    "rayquaza": [
      "machine"
    ],
    "torterra": [
      "machine"
    ],
    "infernape": [
      "machine"
    ],
    "cranidos": [
      "machine"
    ],
    "rampardos": [
      "machine"
    ],
    "shieldon": [
      "machine"
    ],
    "bastiodon": [
      "machine"
    ],
    "gastrodon": [
      "machine"
    ],
    "gible": [
      "machine"
    ],
    "gabite": [
      "machine"
    ],
    "garchomp": [
      "machine"
    ],
    "lucario": [
      "machine"
    ],
    "hippowdon": [
      "machine"
    ],
    "toxicroak": [
      "machine"
    ],
    "rhyperior": [
      "level-up",
      "machine"
    ],
    "gliscor": [
      "machine"
    ],
    "mamoswine": [
      "machine"
    ],
    "gallade": [
      "machine"
    ],
    "probopass": [
      "level-up",
      "machine"
    ],
    "dialga": [
      "machine"
    ],
    "palkia": [
      "machine"
    ],
    "heatran": [
      "level-up",
      "machine"
    ],
    "regigigas": [
      "machine"
    ],
    "giratina-altered": [
      "machine"
    ],
    "arceus": [
      "machine"
    ],
    "pignite": [
      "machine"
    ],
    "emboar": [
      "machine"
    ],
    "roggenrola": [
      "level-up",
      "machine"
    ],
    "boldore": [
      "level-up",
      "machine"
    ],
    "gigalith": [
      "level-up",
      "machine"
    ],
    "timburr": [
      "level-up",
      "machine"
    ],
    "gurdurr": [
      "level-up",
      "machine"
    ],
    "conkeldurr": [
      "level-up",
      "machine"
    ],
    "throh": [
      "machine"
    ],
    "sawk": [
      "machine"
    ],
    "sandile": [
      "machine"
    ],
    "krokorok": [
      "machine"
    ],
    "krookodile": [
      "machine"
    ],
    "darmanitan-standard": [
      "machine"
    ],
    "dwebble": [
      "machine"
    ],
    "crustle": [
      "machine"
    ],
    "scraggy": [
      "machine"
    ],
    "scrafty": [
      "machine"
    ],
    "tirtouga": [
      "machine"
    ],
    "carracosta": [
      "machine"
    ],
    "archen": [
      "machine"
    ],
    "archeops": [
      "machine"
    ],
    "beartic": [
      "machine"
    ],
    "stunfisk": [
      "machine"
    ],
    "mienfoo": [
      "machine"
    ],
    "mienshao": [
      "machine"
    ],
    "golurk": [
      "machine"
    ],
    "bisharp": [
      "machine"
    ],
    "bouffalant": [
      "machine"
    ],
    "durant": [
      "machine"
    ],
    "hydreigon": [
      "machine"
    ],
    "cobalion": [
      "machine"
    ],
    "terrakion": [
      "level-up",
      "machine"
    ],
    "virizion": [
      "machine"
    ],
    "reshiram": [
      "machine"
    ],
    "zekrom": [
      "machine"
    ],
    "landorus-incarnate": [
      "level-up",
      "machine"
    ],
    "kyurem": [
      "machine"
    ],
    "keldeo-ordinary": [
      "machine"
    ],
    "meloetta-aria": [
      "machine"
    ],
    "chespin": [
      "machine"
    ],
    "quilladin": [
      "machine"
    ],
    "chesnaught": [
      "machine"
    ],
    "bunnelby": [
      "machine"
    ],
    "diggersby": [
      "machine"
    ],
    "pancham": [
      "machine"
    ],
    "pangoro": [
      "machine"
    ],
    "binacle": [
      "machine"
    ],
    "barbaracle": [
      "level-up",
      "machine"
    ],
    "tyrunt": [
      "machine"
    ],
    "tyrantrum": [
      "machine"
    ],
    "amaura": [
      "machine"
    ],
    "aurorus": [
      "machine"
    ],
    "hawlucha": [
      "machine"
    ],
    "carbink": [
      "level-up",
      "machine"
    ],
    "bergmite": [
      "machine"
    ],
    "avalugg": [
      "machine"
    ],
    "zygarde": [
      "machine"
    ],
    "diancie": [
      "level-up",
      "machine"
    ],
    "volcanion": [
      "machine"
    ],
    "crabrawler": [
      "machine"
    ],
    "crabominable": [
      "machine"
    ],
    "rockruff": [
      "level-up",
      "machine"
    ],
    "lycanroc-midday": [
      "level-up",
      "machine"
    ],
    "sandygast": [
      "machine"
    ],
    "palossand": [
      "machine"
    ],
    "minior-red-meteor": [
      "machine"
    ],
    "turtonator": [
      "machine"
    ],
    "tapu-bulu": [
      "machine"
    ],
    "solgaleo": [
      "machine"
    ],
    "buzzwole": [
      "machine"
    ],
    "celesteela": [
      "machine"
    ],
    "guzzlord": [
      "machine"
    ],
    "necrozma": [
      "machine"
    ],
    "marshadow": [
      "machine"
    ],
    "stakataka": [
      "machine"
    ],
    "giratina-origin": [
      "machine"
    ],
    "darmanitan-zen": [
      "machine"
    ],
    "meloetta-pirouette": [
      "machine"
    ],
    "landorus-therian": [
      "level-up",
      "machine"
    ],
    "kyurem-black": [
      "machine"
    ],
    "kyurem-white": [
      "machine"
    ],
    "keldeo-resolute": [
      "machine"
    ],
    "pinsir-mega": [
      "machine"
    ],
    "gyarados-mega": [
      "machine"
    ],
    "aerodactyl-mega": [
      "machine"
    ],
    "mewtwo-mega-x": [
      "machine"
    ],
    "mewtwo-mega-y": [
      "machine"
    ],
    "heracross-mega": [
      "machine"
    ],
    "tyranitar-mega": [
      "level-up",
      "machine"
    ],
    "blaziken-mega": [
      "machine"
    ],
    "mawile-mega": [
      "machine"
    ],
    "aggron-mega": [
      "machine"
    ],
    "absol-mega": [
      "machine"
    ],
    "garchomp-mega": [
      "machine"
    ],
    "lucario-mega": [
      "machine"
    ],
    "swampert-mega": [
      "machine"
    ],
    "gallade-mega": [
      "machine"
    ],
    "steelix-mega": [
      "level-up",
      "machine"
    ],
    "diancie-mega": [
      "level-up",
      "machine"
    ],
    "groudon-primal": [
      "machine"
    ],
    "rayquaza-mega": [
      "machine"
    ],
    "camerupt-mega": [
      "machine"
    ],
    "salamence-mega": [
      "machine"
    ],
    "dugtrio-alola": [
      "machine"
    ],
    "geodude-alola": [
      "level-up",
      "machine"
    ],
    "graveler-alola": [
      "level-up",
      "machine"
    ],
    "golem-alola": [
      "level-up",
      "machine"
    ],
    "grimer-alola": [
      "machine"
    ],
    "muk-alola": [
      "machine"
    ],
    "marowak-alola": [
      "machine"
    ],
    "zygarde-10": [
      "machine"
    ],
    "zygarde-50": [
      "machine"
    ],
    "zygarde-complete": [
      "machine"
    ],
    "lycanroc-midnight": [
      "level-up",
      "machine"
    ],
    "minior-orange-meteor": [
      "machine"
    ],
    "minior-yellow-meteor": [
      "machine"
    ],
    "minior-green-meteor": [
      "machine"
    ],
    "minior-blue-meteor": [
      "machine"
    ],
    "minior-indigo-meteor": [
      "machine"
    ],
    "minior-violet-meteor": [
      "machine"
    ],
    "minior-red": [
      "machine"
    ],
    "minior-orange": [
      "machine"
    ],
    "minior-yellow": [
      "machine"
    ],
    "minior-green": [
      "machine"
    ],
    "minior-blue": [
      "machine"
    ],
    "minior-indigo": [
      "machine"
    ],
    "minior-violet": [
      "machine"
    ],
    "marowak-totem": [
      "machine"
    ],
    "rockruff-own-tempo": [
      "level-up",
      "machine"
    ],
    "lycanroc-dusk": [
      "level-up",
      "machine"
    ],
    "necrozma-dusk": [
      "machine"
    ],
    "necrozma-dawn": [
      "machine"
    ],
    "necrozma-ultra": [
      "machine"
    ]
  }
}
