{
  "id": 501,
  "name": "quick-guard",
  "caption": "Quick Guard",
  "type": "fighting",
  "damageCategory": "status",
  "power": null,
  "accuracy": null,
  "pp": 15,
  "priority": 3,
  "gen": "generation-v",
  "effect": {
    "short": "Prevents any priority moves from hitting friendly Pokémon this turn.",
    "full": "Moves with priority greater than 0 will not hit friendly Pokémon for the remainder of this turn.  If the user is last to act this turn, this move will fail.\n\nThis move cannot be selected by assist or metronome."
  },
  "flavorTexts": [
    {
      "text": "The user protects itself and its allies from\npriority moves.",
      "versionGroup": "ultra-sun-ultra-moon"
    },
    {
      "text": "The user protects itself and its allies from\npriority moves.",
      "versionGroup": "sun-moon"
    },
    {
      "text": "The user protects itself and its allies\nfrom priority moves.",
      "versionGroup": "omega-ruby-alpha-sapphire"
    },
    {
      "text": "The user protects itself and its allies\nfrom priority moves.",
      "versionGroup": "x-y"
    },
    {
      "text": "The user protects itself and its allies\nfrom priority moves. If used in\nsuccession, its chance of failing rises.",
      "versionGroup": "black-2-white-2"
    },
    {
      "text": "The user protects itself and its allies\nfrom priority moves. If used in\nsuccession, its chance of failing rises.",
      "versionGroup": "black-white"
    }
  ]
}
